STAGATE_pyG/STAGATE.py
STAGATE_pyG/Train_STAGATE.py
STAGATE_pyG/__init__.py
STAGATE_pyG/gat_conv.py
STAGATE_pyG/utils.py
STAGATE_pyG-1.0.0.dist-info/LICENSE
STAGATE_pyG-1.0.0.dist-info/METADATA
STAGATE_pyG-1.0.0.dist-info/WHEEL
STAGATE_pyG-1.0.0.dist-info/top_level.txt
STAGATE_pyG-1.0.0.dist-info/RECORD
